{
  "type": "Program",
  "body": [
    {
      "type": "ExportAllDeclaration",
      "source": {
        "type": "Literal",
        "value": "./0-legacy",
        "raw": "'./0-legacy'",
        "range": [
          14,
          26
        ],
        "loc": {
          "start": {
            "line": 1,
            "column": 14
          },
          "end": {
            "line": 1,
            "column": 26
          }
        }
      },
      "range": [
        0,
        28
      ],
      "loc": {
        "start": {
          "line": 1,
          "column": 0
        },
        "end": {
          "line": 1,
          "column": 28
        }
      }
    },
    {
      "type": "ExportAllDeclaration",
      "source": {
        "type": "Literal",
        "value": "./1-new",
        "raw": "'./1-new'",
        "range": [
          43,
          52
        ],
        "loc": {
          "start": {
            "line": 2,
            "column": 14
          },
          "end": {
            "line": 2,
            "column": 23
          }
        }
      },
      "range": [
        29,
        54
      ],
      "loc": {
        "start": {
          "line": 2,
          "column": 0
        },
        "end": {
          "line": 2,
          "column": 25
        }
      }
    },
    {
      "type": "ExportAllDeclaration",
      "source": {
        "type": "Literal",
        "value": "./2-api",
        "raw": "'./2-api'",
        "range": [
          69,
          78
        ],
        "loc": {
          "start": {
            "line": 3,
            "column": 14
          },
          "end": {
            "line": 3,
            "column": 23
          }
        }
      },
      "range": [
        55,
        80
      ],
      "loc": {
        "start": {
          "line": 3,
          "column": 0
        },
        "end": {
          "line": 3,
          "column": 25
        }
      }
    }
  ],
  "sourceType": "module",
  "range": [
    0,
    80
  ],
  "loc": {
    "start": {
      "line": 1,
      "column": 0
    },
    "end": {
      "line": 3,
      "column": 25
    }
  },
  "comments": []
}